securecred/__init__.py
securecred/main.py
securecred-0.1.0.dist-info/WHEEL
securecred-0.1.0.dist-info/METADATA
securecred-0.1.0.dist-info/RECORD
